datadir/__init__.py
datadir/datadirectory.py
datadir-1.1.0.dist-info/LICENSE
datadir-1.1.0.dist-info/METADATA
datadir-1.1.0.dist-info/WHEEL
datadir-1.1.0.dist-info/top_level.txt
datadir-1.1.0.dist-info/RECORD
