Metadata-Version: 2.1
Name: datadir
Version: 1.1.0
Summary: A data directory helper Python package
Home-page: https://github.com/hboueix/datadir
Author: Hugo Boueix
License: MIT
Project-URL: Issue tracker, https://github.com/hboueix/datadir/issues
Classifier: Development Status :: 5 - Production/Stable
Classifier: License :: OSI Approved :: MIT License
Classifier: Intended Audience :: Developers
Classifier: Natural Language :: English
Classifier: Operating System :: OS Independent
Classifier: Programming Language :: Python :: 3.8
Classifier: Programming Language :: Python :: 3.9
Classifier: Programming Language :: Python :: 3.10
Classifier: Topic :: Software Development :: Libraries
Classifier: Topic :: Software Development :: Libraries :: Python Modules
Classifier: Topic :: Utilities
Classifier: Typing :: Typed
Requires-Python: >=3.8.0
License-File: LICENSE
Requires-Dist: openpyxl >=3.0.0
Requires-Dist: pandas >=1.5.0
Requires-Dist: pyarrow >=10.0.0
Provides-Extra: test
Requires-Dist: pytest ; extra == 'test'
Requires-Dist: mutatest ; extra == 'test'
